gaia_image_processing/__init__.py
gaia_image_processing/image_processing.py
gaia_image_processing-1.0.0.dist-info/METADATA
gaia_image_processing-1.0.0.dist-info/RECORD
gaia_image_processing-1.0.0.dist-info/WHEEL
gaia_image_processing-1.0.0.dist-info/top_level.txt
tests/__init__.py
tests/test_image_processing.py
