Metadata-Version: 2.1
Name: gaia-image-processing
Version: 1.0.0
Summary: Image processing module for the gaia boat.
Home-page: https://github.com/gaia-boat/image-processing
License: GNU
Keywords: gaia,boat,pi2
Platform: UNKNOWN
Classifier: Development Status :: 5 - Production/Stable
Classifier: Intended Audience :: Other Audience
Classifier: Natural Language :: Portuguese
Classifier: License :: OSI Approved :: GNU General Public License v3 or later (GPLv3+)
Classifier: Operating System :: OS Independent
Classifier: Programming Language :: Python
Classifier: Programming Language :: Python :: 3.6
Classifier: Programming Language :: Python :: Implementation :: CPython
Classifier: Programming Language :: Python :: Implementation :: PyPy
Classifier: Topic :: Software Development :: Libraries :: Python Modules
